{
  "speech": [
    {
      "conditions": {
        "relation": "friendly"
      },
      "lines": [
        "我看到人肉了!",
        "我聞到人肉了!",
        "人肉在那?",
        "你要啥?",
        "在這糟透的三天只吃了長蛆的麵包!",
        "又是長蛆的麵包? 我要人肉!",
        "我已經等不及要再拿人肉塞牙縫了!",
        "再找啥?",
        "這裡的空氣臭死人了.",
        "我們應該打碎他們的骨頭然後大快朵頤地吃他們的肉!",
        "咒那些王國的子民去死!咒那些汙穢的精靈去死!",
        "咒那些都靈一族去死",
        "這些破衣服臭死了!",
        "世界上的人們該被粉碎殆盡.",
        "摧毀!把那些自由自民徹底摧毀!",
        "是人肉!",
        "最近的人肉在哪? 我要餓扁了!",
        "記好了是誰把那些卑劣的矮人從山上趕下來的!",
        "我們把矮人從他們的礦動趕了出去! 然後現在他們都沒有再回來了!"
      ]
    },
    {
      "conditions": {
        "relation": "friendly",
        "rank": ">=thrall"
      },
      "lines": [
        "我們共同祀奉同個主人, #p.",
        "我們就像瘟疫一樣衝進自由之民的土地! 把一切的生命體全部消失殆盡!",
        "我們的座狼是所有哥布林族群中最汙穢,最兇猛的!"
      ]
    },
    {
      "conditions": {
        "relation": "friendly",
        "rank": "<snaga"
      },
      "lines": [
        "你祀奉誰啊?",
        "你不配騎最惡劣的座狼!"
      ]
    },
    {
      "conditions": {
        "relation": "friendly",
        "rank": "<raider"
      },
      "lines": [
        "別擋路, 蟲子!",
        "滾去工作, 敗類!",
        "你跟史那家一樣臭!",
        "我們的座狼可是血腥的! 所以注意點, 否則我就讓牠們咬你了! 哈!",
        "別脫隊, #p, 否則強獸人會把你好好修理一頓!"
      ]
    },
    {
      "conditions": {
        "relation": "friendly",
        "rank": ">=raider"
      },
      "lines": [
        "#p,沒過多久! 我們就要與那些卑劣的人民打仗啦!",
        "你這人還不錯嘛!",
        "你這人還不錯嘛, #p! 雖然你身上還是有股遊俠的騷味!"
      ]
    },
    {
      "conditions": {
        "relation": "friendly",
        "rank": ">=raider & <warlord"
      },
      "lines": [
        "骯髒的蟲子! 噢, 是你啊, #p...",
        "你仍然不像是個哥布林啊, #p!",
        "準備好要上戰場了嗎! 隨時都要做好應對!"
      ]
    },
    {
      "conditions": {
        "relation": "friendly",
        "rank": "<ravager"
      },
      "lines": [
        "只要你肯給我人肉吃,我就不吃你! 哈! 哈!",
        "你再找啥, 蛆蟲?",
        "聽重命令, 垃圾!",
        "別站在那邊傻愣! 做事啊!",
        "我不相信你, 蟲子!",
        "別停留, 渣仔!",
        "你是打算要來打場架嘛?",
        "我不相信卑劣的人類!"
      ]
    },
    {
      "conditions": {
        "relation": "friendly",
        "rank": ">=scourge"
      },
      "lines": [
        "尊崇你的指揮, #p!",
        "山裡有下達甚麼指示嗎, #p?",
        "強獸人們對你有高度的讚賞, #p."
      ]
    },
    {
      "conditions": {
        "relation": "friendly",
        "rank": "<scourge"
      },
      "lines": [
        "喂! 注意你的言行!",
        "有股惡臭味. 原來是你啊, #p! 快滾!",
        "你好臭!",
        "你跟一塊腐肉一樣臭,蟲子!"
      ]
    },
    {
      "conditions": {
        "relation": "friendly",
        "rank": "<warlord"
      },
      "lines": [
        "你不像個哥布林!",
        "你要甚麼?"
      ]
    },
    {
      "conditions": {
        "relation": "friendly",
        "rank": ">=warlord"
      },
      "lines": [
        "剛達巴那邊有下達甚麼命令嗎?",
        "剛達巴那邊有下達甚麼指示嗎, #p?",
        "老大要我們做甚麼?",
        "聽重你的指示,垃圾! ...我是說 #p!",
        "我要告訴兄弟們視察的時候到了!",
        "我會隨時為你準備你頭座狼!"
      ]
    },
    {
      "conditions": {
        "relation": "friendly",
        "rank": ">=chieftain"
      },
      "lines": [
        "所以? 你是新的老大嗎?",
        "我們為你而戰!",
        "帶我們走向世界盡頭, #p!"
      ]
    },
    {
      "conditions": {
        "relation": "hostile"
      },
      "lines": [
        "我要讓你刺得像頭豬一樣再叫!",
        "享用你的最後一口氣,垃圾!",
        "你看起來很好吃!",
        "把那個垃圾殺了!",
        "兄弟們,有肉可以吃了!",
        "我聞到你的恐懼了!",
        "去死吧,垃圾人!",
        "你的血可新鮮了!",
        "我要把你像烤肉串一樣串起來!",
        "你該跑了,蟲子!",
        "靠近點啊我會把你做成肉串!",
        "我們今晚吃人肉!",
        "只要我在，我們會把你處理的只剩下骨頭!",
        "我要享用你的肉,你這汙穢的人!",
        "我要拿你做成晚餐!",
        "你可惹錯獸人了, 垃圾!",
        "我要砍下你的頭, 你這剛鐸的垃圾!",
        "你這個垃圾人竟敢砍我!",
        "渣仔遊俠! 兄弟們,一起上!",
        "蟲子!",
        "垃圾!",
        "臭蟲!",
        "卑劣的史那家!",
        "我放座狼來咬你!",
        "我們的座狼會好好修理你一頓!",
        "你聞起來像是座狼糞You stink of Warg-dung!",
        "你會像摩瑞亞的矮人們下場一樣!"
      ]
    },
    {
      "conditions": {
        "relation": "hostile",
        "player_gender_pref": "m"
      },
      "lines": [
        "兄弟們,做掉他!"
      ]
    },
    {
      "conditions": {
        "relation": "hostile",
        "player_gender_pref": "f"
      },
      "lines": [
        "兄弟們,做掉她!"
      ]
    },
    {
      "conditions": {
        "relation": "hostile",
        "biome": "#home"
      },
      "lines": [
        "你一定是沒看過我們動刀吧, 垃圾?"
      ]
    },
    {
      "conditions": {
        "relation": "hostile",
        "rank": ">=thrall"
      },
      "lines": [
        "你這個打破誓言的垃圾!",
        "打破誓言者! 汙穢的史那家!",
        "我們會把你吃得指剩骨頭, 叛徒!"
      ]
    },
    {
      "conditions": {
        "relation": "friendly",
        "hired": "own"
      },
      "lines": [
        "你為誰效勞,我的主人嗎?",
        "你雖然是我的長官, #p, 但你始終都是個汙穢的蟲子!",
        "帶我們去掠奪, #p!",
        "空氣中充滿著恐懼的惡臭味!",
        "自由之民會被我們的力量消滅!",
        "去死吧! 那些與我們為敵的人都去死吧!",
        "我們該去獵些人肉嗎, #p?",
        "我的肚子想要裝人肉!",
        "我真想獵幾隻臭渣宰.",
        "主咒那些卑劣的遊俠還有他們的同盟去死!",
        "讓我們消滅這世界上的人們!",
        "我們去獵幾隻人!",
        "那些噁心的遊俠不知道等待他們的是甚麼結果!",
        "叫上兄弟們! 要打仗嗎!",
        "叫上座狼!",
        "去獵幾隻矮人!"
      ]
    }
  ]
}